{
  "news_id": "k10011804251000",
  "news_prearranged_time": "2019-02-07 11:30:00",
  "title": "イタリアの大学生が日本の学校の給食を見に来る",
  "title_with_ruby": "イタリアの<ruby>大学生<rt>だいがくせい</rt></ruby>が<ruby>日本<rt>にっぽん</rt></ruby>の<ruby>学校<rt>がっこう</rt></ruby>の<ruby>給食<rt>きゅうしょく</rt></ruby>を<ruby>見<rt>み</rt></ruby>に<ruby>来<rt>く</rt></ruby>る",
  "outline_with_ruby": "<p>イタリアの<ruby>大学<rt>だいがく</rt></ruby>で<ruby>世界<rt>せかい</rt></ruby>の<ruby>食事<rt>しょくじ</rt></ruby>の<ruby>文化<rt>ぶんか</rt></ruby>を<ruby>勉強<rt>べんきょう</rt></ruby>している<ruby>学生<rt>がくせい</rt></ruby>１４<ruby>人<rt>にん</rt></ruby>が、<ruby>日本<rt>にっぽん</rt></ruby>の<a href='javascript:void(0)' class='dicWin' id='id-0000'><ruby>給食<rt>きゅうしょく</rt></ruby></a>を<ruby>見<rt>み</rt></ruby>るために<ruby>山形県<rt>やまがたけん</rt></ruby><ruby>鶴岡市<rt>つるおかし</rt></ruby>へ<ruby>来<rt>き</rt></ruby>ました。",
  "has_news_web_image": true,
  "has_news_web_movie": false,
  "has_news_easy_image": false,
  "has_news_easy_movie": false,
  "has_news_easy_voice": true,
  "news_web_image_uri": "https://www3.nhk.or.jp/news/html/20190205/../20190205/K10011804251_1902051533_1902051537_01_02.jpg",
  "news_web_movie_uri": "",
  "news_easy_image_uri": "''",
  "news_easy_movie_uri": "''",
  "news_easy_voice_uri": "k10011804251000.mp4",
  "url": "http://www3.nhk.or.jp/news/easy/k10011804251000/k10011804251000.html"
}